README
setup.py
kippt/__init__.py
kippt/clips.py
kippt/kippt.py
kippt/lists.py
kippt/notifications.py
kippt/users.py
kippt.egg-info/PKG-INFO
kippt.egg-info/SOURCES.txt
kippt.egg-info/dependency_links.txt
kippt.egg-info/requires.txt
kippt.egg-info/top_level.txt