Metadata-Version: 1.0
Name: kippt
Version: 2.0.0
Summary: Kippt.com API wrapper for Python
Home-page: https://github.com/thomasbiddle/Kippt-Python-Wrapper
Author: TJ (Thomas) Biddle
Author-email: me@ThomasBiddle.com
License: MIT
Platform: UNKNOWN
